abusentry/__init__.py
abusentry/__version__.py
abusentry/abusentry.py
abusentry/decode.py
abusentry/digs.py
abusentry/dnscheck.py
abusentry/ipcheck.py
abusentry/mailer.py
abusentry/malvera.py
abusentry/sniper.py
abusentry/strip.py
abusentry/unshorten.py
abusentry/urlscan.py
abusentry/virustotal.py
abusentry/whobe.py
abusentry/utils/__init__.py
abusentry/utils/config.py
abusentry/utils/dns.py
abusentry/utils/env.py
abusentry/utils/exceptions.py
abusentry/utils/fangs.py
abusentry/utils/http.py
abusentry/utils/ipaddr.py
abusentry-0.2.3.dist-info/LICENSE.md
abusentry-0.2.3.dist-info/METADATA
abusentry-0.2.3.dist-info/WHEEL
abusentry-0.2.3.dist-info/entry_points.txt
abusentry-0.2.3.dist-info/top_level.txt
abusentry-0.2.3.dist-info/RECORD
