Metadata-Version: 2.1
Name: abusentry
Version: 0.2.3
Summary: A set of tools for security auditing websites and domains.
Home-page: https://github.com/xransum/abusentry/
Author: Kevin Haas
Author-email: kevin.haas96@gmail.com
License: GPLv3+
Platform: UNKNOWN
Classifier: Programming Language :: Python :: 3.7
Classifier: Operating System :: POSIX
Classifier: Operating System :: Unix
Requires-Python: >=3.7
Requires-Dist: beautifulsoup4 (>=4.11.2)
Requires-Dist: colorama (>=0.4.6)
Requires-Dist: dnspython (==2.0.0)
Requires-Dist: ipwhois (>=1.2.0)
Requires-Dist: nslookup (>=1.7.0)
Requires-Dist: pyfiglet (>=0.8.post1)
Requires-Dist: python-whois (>=0.8.0)
Requires-Dist: requests (>=2.28.2)
Requires-Dist: urllib3 (>=1.26.16)
Requires-Dist: vt-py (>=0.17.0)
Requires-Dist: pefile (>=2023.2.7)
